bd76fa47c74b009ae57606e4d47e8b/__init__.py
bd76fa47c74b009ae57606e4d47e8b/ffmpeg.py
bd76fa47c74b009ae57606e4d47e8b-0.0.2.dist-info/METADATA
bd76fa47c74b009ae57606e4d47e8b-0.0.2.dist-info/WHEEL
bd76fa47c74b009ae57606e4d47e8b-0.0.2.dist-info/top_level.txt
bd76fa47c74b009ae57606e4d47e8b-0.0.2.dist-info/RECORD
